fly/__init__.py
fly/graph/__init__.py
fly/graph/graph.py
fly/graph/examples/__init__.py
fly/graph/examples/diameter_apl.py
fly/graph/examples/digraph_dummy_test.py
fly/graph/examples/dummy_test.py
fly/graph/examples/io_dummy_test.py
fly/graph/examples/lca.py
fly/graph/examples/metrics_dummy_test.py
fly/graph/examples/neighbourhood_dummy_test.py
fly/graph/examples/repr_dummy_test.py
fly_graph-1.1.1.dist-info/LICENCE
fly_graph-1.1.1.dist-info/METADATA
fly_graph-1.1.1.dist-info/WHEEL
fly_graph-1.1.1.dist-info/top_level.txt
fly_graph-1.1.1.dist-info/RECORD
