Metadata-Version: 2.1
Name: fly-graph
Version: 1.1.1
Summary: A graph library for FLY language, written in Python
Home-page: https://github.com/bissim/FLY-graph
Author: Simone Bisogno
Author-email: s.bisogno90@gmail.com
License: MIT
Project-URL: Source, https://github.com/bissim/FLY-graph
Project-URL: Tracker, https://github.com/bissim/FLY-graph/issues
Keywords: FLY graph management
Platform: UNKNOWN
Classifier: Programming Language :: Python
Classifier: Programming Language :: Python :: 3
Classifier: Programming Language :: Python :: 3.7
Classifier: License :: OSI Approved :: MIT License
Classifier: Operating System :: OS Independent
Classifier: Development Status :: 6 - Mature
Classifier: License :: OSI Approved :: MIT License
Classifier: Programming Language :: Other
Classifier: Topic :: Software Development :: Libraries :: Python Modules
Requires-Python: ~=3.6
Requires-Dist: networkx
